dicomity/__init__.py
dicomity/dicom.py
dicomity/dictionary.py
dicomity/group.py
dicomity/load.py
dicomity/types.py
dicomity/util.py
dicomity-0.0.9.dist-info/METADATA
dicomity-0.0.9.dist-info/WHEEL
dicomity-0.0.9.dist-info/licenses/LICENSE
dicomity-0.0.9.dist-info/RECORD
